krishanfirstpackage/__init__.py
krishanfirstpackage/sample.py
krishanfirstpackage-0.0.1.dist-info/LICENSE.txt
krishanfirstpackage-0.0.1.dist-info/METADATA
krishanfirstpackage-0.0.1.dist-info/WHEEL
krishanfirstpackage-0.0.1.dist-info/top_level.txt
krishanfirstpackage-0.0.1.dist-info/RECORD
